{
    "bib" : {
        "properties" : {
            "about" : {
                "properties" : {
                    "@type": { "type" : "string", "index": "not_analyzed" },
                    "@id": { "type" : "string", "index": "not_analyzed" },
                    "instanceOf" : {
                        "properties" : {
                            "creator" : {
                                "properties": {
                                    "controlledLabel" : {
                                        "type" : "multi_field",
                                        "fields" : {
                                            "controlledLabel": { "type" : "string", "index": "analyzed" },
                                            "untouched" : { "type" : "string", "index": "not_analyzed" }
                                        }
                                    }
                               }
                           }
                        }
                    }
                 }
             }
        }
        
    }
}
