{

  "marcTypeFromTypeOfRecord": {
    "*": "bib",
    "u": "hold",
    "v": "hold",
    "x": "hold",
    "y": "hold",
    "z": "auth"
  },

  "resourceMaps": {
    "relatorCode": "relatorcodes.json"
  },

  "entityTypeMap": {
    "Authority": {"typeOfRecord": "z", "abstract": true},
    "Holding": {"typeOfRecord": ["u", "v", "x", "y"]},
    "Book": {"typeOfRecord": "a", "bibLevel": "m",
      "instanceTypes": {
        "Audiobook": {"carrierType": "s"},
        "CDBook": {"carrierType": "c", "carrierMaterial": "o"},
        "EBook": {"carrierType": "c", "carrierMaterial": "r"}
      }
    },
    "Serial": {"typeOfRecord": "a", "bibLevel": "s",
      "instanceTypes": {
        "ESerial": {"carrierType": "c", "carrierMaterial": "r"}
      }
    },
    "Cartography": {"typeOfRecord": "e", "bibLevel": "m",
      "instanceTypes": {
        "CDMap": {"carrierType": "c", "carrierMaterial": "o"}
      }
    },
    "Audio": {"typeOfRecord": "i", "abstract": true,
      "Audiobook": {"bibLevel": "m", "TODO": "not 655a=Talböcker"}
    },
    "Music": {"typeOfRecord": "j", "bibLevel": "m",
      "instanceTypes": {
        "MusicCD": {"carrierType": "s", "carrierMaterial": "d"}
      }
    },
    "Digital": {"carrierType": "c", "mixin": true}
  },

  "bib": {

    "000": {
      "[5:6]": {"domainEntity": "Record", "property": "status"},
      "[6:7]": {"domainEntity": "Record", "property": "typeOfRecord"},
      "[7:8]": {"domainEntity": "Record", "property": "bibLevel"},
      "[8:9]": {"domainEntity": "Record", "property": "typeOfControl"},
      "[9:10]": {"domainEntity": "Record", "property": "characterCoding"},
      "[17:18]": {"domainEntity": "Record", "property": "encLevel"},
      "[18:19]": {"domainEntity": "Record", "property": "catForm"},
      "[19:20]": {"domainEntity": "Record", "property": "linked"},
      "[20:24]": {"domainEntity": "Record", "property": "entryMap"}
    },

    "001": {"domainEntity": "Record", "property": "controlNumber"},
    "003": {"domainEntity": "Record", "property": "systemName"},
    "005": {"property": "updated", "parse": {"dateTime": "yyyymmddhhmmss"}},

    "007": {
      "[0:1]": {"domainEntity": "Record", "property": "carrierType"},
      "[1:2]": {"domainEntity": "Record", "property": "carrierMaterial"},
      "_Microform": {
      "6-8": {"propId": "reductionExactRightJustifiedWithLeadingZero"}
      },
      "_MotionPicture": {
        "17-22": {"propId": "filmInspectionDate"}
      }
    },

    "006": {
      "[0:0]": {},
      "tokenSyncedWith": "typeOfRecord",
      "repeats": "008"
    },

    "008": {
      "repeatedBy": "006",
      "[7:11]": {"propId": "yearTime1"},
      "[11:15]": {"propId": "yearTime2"},
      "[35:38]": {"propId": "language"},

      "0+6": {"range": "date"},
      "publicationStatus": {"dateTypeFor": "008.0+6"},
      "7+4": {"id": "yearTime1", "range": "date"},
      "11+4": {"id": "yearTime2", "range": "date"},
      "catalogingSource": {},
      "modifiedRecord": {"detail": 0},
      "language": {"sameValueAs": [null]}
    },

    "010": {"domainEntity": "Instance", "$a": {"property": "lccn"}},

    "020": {
      "domainEntity": "Instance",
      "addLink": "identifier",
      "matchDomain": {
        "EBook": {"addLink": "commonEndeavor"}
      },
      "rangeEntity": "Identifier",
      "$a": {
        "property": "identifierValue",
        "pattern": "(\\S+)(?:\\s*\\(([^)]+)\\))?", "properties": ["identifierValue", "identifierNote"],
        "defaults": {
          "identifierScheme": "ISBN"
        }
      },
      "$c": {"domainEntity": "Instance", "property": "availability"},
      "$z": {
        "property": "identifierValue",
        "defaults": {
          "identifierScheme": "ISBN",
          "identifierStatus": "canceledInvalid"
        }
      }
    },

    "024": {
      "domainEntity": "Instance",
      "addLink": "identifier",
      "rangeEntity": "Identifier",
      "$a": {"property": "identifierValue"},
      "TODO": "identifierScheme from ind2?"
    },

    "034": {"entity": "Cartography", "$_": {}},

    "035": {
      "domainEntity": "Record",
      "$a": {"property": "system-number"},
      "$9": {"property": "librisIII-number"}
    },

    "040": {
      "domainEntity": "Record",
      "$a": {"link": "originalCatalogingAgency", "rangeEntity": "Organization", "property": "name"},
      "$b": {"property": "language"},
      "$c": {"link": "transcribingAgency", "rangeEntity": "Organization", "property": "name"},
      "$d": {"link": "modifyingAgency", "rangeEntity": "Organization", "property": "name"},
      "$e": {"property": "descriptionRules"}
    },
    "TODO:041": {"$a": {"defaultFrom": ["240.a"]}},
    "042": {
      "entity": "Record",
      "$a": {"property": "authenticationCode"},
      "$9": {"property": "bibliographyCode"}
    },
    "043": {"ignored": true},

    "050": {
      "domainEntity": "Work",
      "$a": {"property": "class-lcc"},
      "$b": {"ignored": true}
    },

    "082": {
      "domainEntity": "Work",
      "$a": {"property": "class-ddc"},
      "$2": {"ignored": true}
    },

    "072": {
      "inherit": "084"
    },

    "084": {
      "link": "class",
      "matchDomain": {
        "Work": {"link": "class"}, "Holding": {"link": "callno"}
      },
      "rangeEntity": "ClassificationEntity",
      "$a": {"property": "classNumber"},
      "$2": {"property": "classScheme"},
      "$b": {"property": "classItem"}
    },

    "100": {
      "domainEntity": "Work",
      "rangeEntity": "Person",
      "matchInd1": {
        "1": {
          "$a": {"split": ",", "...": "..."}
        },
        "3": {
          "rangeEntity": "Family"
        }
      },
      "addLink": "creator",
      "computeLinks": {"use": "$4", "mapping": "relatorCode"},
      "$a": {"property": "label", "pattern": "([^,]+)(?:,\\s*([^,]+))", "properties": ["familyName", "givenName"], "required": true},
      "$d": {"property": "lifeSpan", "pattern": "(\\d+)(?:-(\\d+))?", "properties": ["birthYear", "deathYear"], "required": true},
      "create": {"label": {"format": "%s, %s, %s-%s", "source": ["familyName", "givenName", "birthYear", "deathYear"]}}
    },
    "110": {
      "domainEntity": "Work",
      "rangeEntity": "Organization",
      "link": "creator",
      "$a": {"property": "label"}
    },
    "111": {
    },

    "210": {
      "domainEntity": "Instance",
      "link": "abbreviatedTitle",
      "rangeEntity": "TitleEntity",
      "$a": {"property": "titleValue"},
      "$b": {"property": "titleQualifier"},
      "$2": {"property": "titleSource"}
    },
    "222": {
      "inherit": "210",
      "link": "keyTitle",
      "$2": null
    },
    "240": {
      "domainEntity": "Work",
      "$a": {"property": "uniformTitle"}
    },
    "242": {
      "inherit": "245",
      "TODO": "translatedTitle? merge into 245?"
    },
    "245": {
      "i1": {},
      "i2": {},
      "domainEntity": "Instance",
      "link": "title",
      "rangeEntity": "TitleEntity",
      "$a": {"property": "titleValue"},
      "$b": {"property": "subtitle"},
      "$c": {"domainEntity": "Instance", "property": "responsibilityStatement"},
      "$f": {"property": "titleDate"},
      "$h": {"domainEntity": "Instance", "property": "mediaTerm"},
      "$n": {"property": "partEnumeration"},
      "$p": {"property": "partTitle"}
    },
    "246": {
      "inherit": "245",
      "link": "titleVariation"
    },
    "247": {
      "inherit": "245",
      "link": "titleVariation"
    },

    "250": {
      "domainEntity": "Instance",
      "link": "editionStatement",
      "rangeEntity": "EditionEntity",
      "$a": {"property": "edition"},
      "$b": {"property": "editionResponsibility"}
    },

    "255": {"TODO": {"specificDomainEntities": ["Cartography"]}, "$_": {}},

    "256": {
      "domainEntity": "Instance",
      "$a": {"property": "fileType"}
    },

    "260": {
      "domainEntity": "Instance",
      "addLink": "provider",
      "splitLink": [
        {"codes": ["a", "b", "c"], "addLink": "publication"},
        {"codes": ["e", "f", "g"], "addLink": "manufacture"}
      ],
      "TODO": ["splitByRepetitionAndInterpunctionPattern", "moveTo:264"],
      "rangeEntity": "ProviderEvent",
      "i1": {"property": "latest", "valueMap": {"2": false, "3": true}},
      "$a": {"link": "place", "rangeEntity": "Place", "property": "label"},
      "$b": {"property": "providerName"},
      "$c": {"property": "providerDate"},
      "$e": {"link": "place", "rangeEntity": "Place", "property": "label"},
      "$f": {"property": "providerName"},
      "$g": {"property": "providerDate"},
      "$3": {"property": "scopeNote", "position": 0}
    },

    "300": {
      "entity": "Instance",
      "$a": {"property": "extent"},
      "$c": {"property": "dimensions"},
      "$b": {"property": "otherPhysicalDetails"},
      "$e": {"property": "accompanyingMaterial"},
      "$3": {
        "previousEndsWith": "+",
        "property": "materialsSpecified"
      }
    },

    "310": {
      "domainEntity": "Instance",
      "$a": {"property": "frequency"}
    },

    "321": {},
    "362": {},

    "440": {"prefer": "490"},

    "500": {"$a": {"domainEntity": "Instance", "property": "note"}},
    "504": {"$a": {"domainEntity": "Instance", "property": "supplementaryContentNote"}},
    "505": {"$a": {"domainEntity": "Instance", "property": "listOfContents"}},
    "508": {"$a": {"domainEntity": "Instance", "property": "creditsNote"}},

    "511": {
      "$a": {
        "matchInd1": {"1": {"property": "participantNote"}},
        "domainEntity": "Instance",
        "addProperty": "performerNote"
      }
    },

    "520": {"domainEntity": "Instance", "$a": {"property": "summary"}},

    "538": {"$a": {"domainEntity": "Instance", "property": "systemRequirements"}},

    "599": {"$a": {"domainEntity": "Record", "property": "comment"}},

    "600": {"inherit": "100", "addLink": "subject"},
    "610": {"inherit": "110", "addLink": "subject"},
    "611": {"inherit": "111", "addLink": "subject"},
    "650": {
      "domain": "Work",
      "addLink": "subject",
      "rangeEntity": "Concept",
      "$a": {"property": "prefLabel"},
      "$2": {"link": "inScheme", "rangeEntity": "ConceptScheme", "property": "notation"}
    },
    "651": {
      "inherit": "650",
      "rangeEntity": "Place",
      "$a": {"property": "label"}
    },

    "700": {"inherit": "100", "addLink": "contributor"},
    "710": {"inherit": "110", "addLink": "contributor"},
    "711": {"inherit": "111"},

    "740": {
      "addLink": "relation",
      "rangeEntity": "Work",
      "$a": {"property": "title"}
    },

    "785": {
      "addLink": "succeeding",
      "rangeEntity": "Instance",
      "$t": {"property": "title"}
    },

    "883": {},

    "976": {
      "domainEntity": "Work",
      "addLink": "subject",
      "rangeEntity": "Concept",
      "TODO": "conceptScheme from ind2?",
      "$a": {"property": "notation"},
      "$b": {"property": "prefLabel"}
    }

  },

  "auth": {
  },

  "hold": {
    "entityTypeMap": "Holding"
  }

}
