{
    "_whelks": [
        {
            "libris":{
                "_class" : "se.kb.libris.whelks.http.HttpStandardWhelk",
                "_plugins": [
                    "index",
                    "flatstorage",
                    "search",
                    "remotesearch",
                    "metasearch",
                    "documentapi",
                    "marcconverter",
                    "turtleconverter",
                    "entityextractor",
                    "jsonldlinkfinder",
                    "namecomplete",
                    "nameexpander",
                    "subjcomplete",
                    "fieldsearch"
                ],
                "contentRoot" : "/",
                "docBaseUri" : "http://libris.kb.se/"
            }
        },
        {
            "resource":{
                "_class" : "se.kb.libris.whelks.http.HttpStandardWhelk",
                "_plugins" : ["diskstorage", "documentapi", "resourcelist", "marcmap", "search", "isxntool" ]
            }
        }
    ]
}
